{
	"name": "AWS_State",
	"properties": {
		"activities": [
			{
				"name": "Copy Mrr_State",
				"type": "Copy",
				"dependsOn": [
					{
						"activity": "sp_trunc_Mrr_State",
						"dependencyConditions": [
							"Succeeded"
						]
					}
				],
				"policy": {
					"timeout": "7.00:00:00",
					"retry": 0,
					"retryIntervalInSeconds": 30,
					"secureOutput": false,
					"secureInput": false
				},
				"userProperties": [],
				"typeProperties": {
					"source": {
						"type": "SqlServerSource",
						"queryTimeout": "02:00:00",
						"partitionOption": "None"
					},
					"sink": {
						"type": "AzureSqlSink"
					},
					"enableStaging": true,
					"stagingSettings": {
						"linkedServiceName": {
							"referenceName": "st_error_log",
							"type": "LinkedServiceReference"
						}
					},
					"translator": {
						"type": "TabularTranslator",
						"mappings": [
							{
								"source": {
									"name": "ID",
									"type": "Int32",
									"physicalType": "int"
								},
								"sink": {
									"name": "ID",
									"type": "Int32",
									"physicalType": "int"
								}
							},
							{
								"source": {
									"name": "State",
									"type": "String",
									"physicalType": "nvarchar"
								},
								"sink": {
									"name": "State",
									"type": "String",
									"physicalType": "nvarchar"
								}
							},
							{
								"source": {
									"name": "Code",
									"type": "String",
									"physicalType": "nvarchar"
								},
								"sink": {
									"name": "Code",
									"type": "String",
									"physicalType": "nvarchar"
								}
							}
						],
						"typeConversion": true,
						"typeConversionSettings": {
							"allowDataTruncation": true,
							"treatBooleanAsNumber": false
						}
					}
				},
				"inputs": [
					{
						"referenceName": "tbl_State",
						"type": "DatasetReference"
					}
				],
				"outputs": [
					{
						"referenceName": "Mrr_State",
						"type": "DatasetReference"
					}
				]
			},
			{
				"name": "sp_trunc_Mrr_State",
				"type": "SqlServerStoredProcedure",
				"dependsOn": [],
				"policy": {
					"timeout": "7.00:00:00",
					"retry": 0,
					"retryIntervalInSeconds": 30,
					"secureOutput": false,
					"secureInput": false
				},
				"userProperties": [],
				"typeProperties": {
					"storedProcedureName": "[srv].[sp_trunc_Mrr_State]"
				},
				"linkedServiceName": {
					"referenceName": "sqldb_egbi_dev",
					"type": "LinkedServiceReference"
				}
			}
		],
		"folder": {
			"name": "Service/Mrr"
		},
		"annotations": [],
		"lastPublishTime": "2020-10-11T13:21:45Z"
	},
	"type": "Microsoft.DataFactory/factories/pipelines"
}