{
	"name": "EntranceReason",
	"properties": {
		"linkedServiceName": {
			"referenceName": "sql_rptsrv",
			"type": "LinkedServiceReference"
		},
		"folder": {
			"name": "SQLSRV-RPTSRV/EDHR"
		},
		"annotations": [],
		"type": "SqlServerTable",
		"schema": [
			{
				"name": "ID",
				"type": "int",
				"precision": 10
			},
			{
				"name": "_Description",
				"type": "nvarchar"
			},
			{
				"name": "_Obsolete",
				"type": "bit"
			}
		],
		"typeProperties": {
			"schema": "dbo",
			"table": "_EntranceReason"
		}
	}
}