{
	"name": "SRV_SERIALS",
	"properties": {
		"linkedServiceName": {
			"referenceName": "sqlsrv_sap",
			"type": "LinkedServiceReference"
		},
		"folder": {
			"name": "SQLSRV-SAP/NewQcoreDB"
		},
		"annotations": [],
		"type": "SqlServerTable",
		"schema": [
			{
				"name": "DocEntry",
				"type": "int",
				"precision": 10
			},
			{
				"name": "LineId",
				"type": "int",
				"precision": 10
			},
			{
				"name": "VisOrder",
				"type": "int",
				"precision": 10
			},
			{
				"name": "Object",
				"type": "nvarchar"
			},
			{
				"name": "LogInst",
				"type": "int",
				"precision": 10
			},
			{
				"name": "U_SerialNo",
				"type": "nvarchar"
			},
			{
				"name": "U_Rma",
				"type": "nvarchar"
			}
		],
		"typeProperties": {
			"schema": "dbo",
			"table": {
				"value": "@@SRV_SERIALS",
				"type": "Expression"
			}
		}
	},
	"type": "Microsoft.DataFactory/factories/datasets"
}